lkg_quilt/__main__.py
lkg_quilt-1.0.1.dist-info/METADATA
lkg_quilt-1.0.1.dist-info/WHEEL
lkg_quilt-1.0.1.dist-info/entry_points.txt
lkg_quilt-1.0.1.dist-info/top_level.txt
lkg_quilt-1.0.1.dist-info/RECORD
