Metadata-Version: 2.1
Name: lkg-quilt
Version: 1.0.1
Summary: Quilt Generator from Lightfield Captures
Home-page: https://github.com/jaxzin/lkg-quilt
Author: Brian Jackson
Author-email: brian@jaxzin.com
Classifier: Development Status :: 4 - Beta
Classifier: Intended Audience :: Developers
Classifier: Topic :: Multimedia :: Graphics
Classifier: License :: OSI Approved :: MIT License
Classifier: Programming Language :: Python :: 3
Classifier: Programming Language :: Python :: 3.12
Requires-Python: >=3.12
Requires-Dist: ffmpeg-python
